afkak/__init__.py
afkak/_group.py
afkak/_protocol.py
afkak/_util.py
afkak/brokerclient.py
afkak/client.py
afkak/codec.py
afkak/common.py
afkak/consumer.py
afkak/kafkacodec.py
afkak/partitioner.py
afkak/producer.py
afkak/test/__init__.py
afkak/test/endpoints.py
afkak/test/fixtures.py
afkak/test/logtools.py
afkak/test/service.py
afkak/test/test_brokerclient.py
afkak/test/test_client.py
afkak/test/test_client_integration.py
afkak/test/test_codec.py
afkak/test/test_common.py
afkak/test/test_consumer.py
afkak/test/test_consumer_integration.py
afkak/test/test_failover_integration.py
afkak/test/test_group.py
afkak/test/test_kafkacodec.py
afkak/test/test_package.py
afkak/test/test_partitioner.py
afkak/test/test_performance_integration.py
afkak/test/test_producer.py
afkak/test/test_producer_integration.py
afkak/test/test_protocol.py
afkak/test/test_util.py
afkak/test/testutil.py
afkak/test/int/__init__.py
afkak/test/int/fixtures.py
afkak/test/int/intutil.py
afkak/test/int/service.py
afkak/test/int/test_client_integration.py
afkak/test/int/test_consumer_integration.py
afkak/test/int/test_failover_integration.py
afkak/test/int/test_group_integration.py
afkak/test/int/test_performance_integration.py
afkak/test/int/test_producer_integration.py
afkak-21.5.0.post0.dist-info/AUTHORS.md
afkak-21.5.0.post0.dist-info/LICENSE
afkak-21.5.0.post0.dist-info/METADATA
afkak-21.5.0.post0.dist-info/WHEEL
afkak-21.5.0.post0.dist-info/top_level.txt
afkak-21.5.0.post0.dist-info/zip-safe
afkak-21.5.0.post0.dist-info/RECORD
