Metadata-Version: 2.1
Name: afkak
Version: 21.5.0.post0
Summary: Twisted Python client for Apache Kafka
Home-page: https://github.com/ciena/afkak
Author: Robert Thille
Author-email: rthille@ciena.com
Maintainer: Tom Most
Maintainer-email: twm@freecog.net
License: Apache License 2.0
Project-URL: Documentation, https://afkak.readthedocs.io/en/latest/
Project-URL: Source, https://github.com/ciena/afkak
Project-URL: Issues, https://github.com/ciena/afkak/issues
Keywords: Kafka client,distributed messaging,txkafka
Platform: UNKNOWN
Classifier: Development Status :: 5 - Production/Stable
Classifier: Framework :: Twisted
Classifier: Intended Audience :: Developers
Classifier: License :: OSI Approved :: Apache Software License
Classifier: Operating System :: MacOS :: MacOS X
Classifier: Operating System :: POSIX
Classifier: Programming Language :: Python :: 3
Classifier: Programming Language :: Python :: 3.5
Classifier: Programming Language :: Python :: 3.6
Classifier: Programming Language :: Python :: 3.7
Classifier: Programming Language :: Python :: 3.8
Classifier: Programming Language :: Python :: Implementation :: CPython
Classifier: Programming Language :: Python :: Implementation :: PyPy
Classifier: Topic :: Communications
Classifier: Topic :: System :: Distributed Computing
Requires-Python: !=3.0.*, !=3.1.*, !=3.2.*, <4
Requires-Dist: attrs (>=19.2.0)
Requires-Dist: Twisted (>=18.7.0)
Provides-Extra: fastmurmur2
Requires-Dist: pyhash ; extra == 'fastmurmur2'
Provides-Extra: snappy
Requires-Dist: python-snappy (>=0.5) ; extra == 'snappy'
